[{"login":"jperrin","id":8331520,"avatar_url":"https://avatars1.githubusercontent.com/u/8331520?v=3","gravatar_id":"","url":"https://api.github.com/users/jperrin","html_url":"https://github.com/jperrin","followers_url":"https://api.github.com/users/jperrin/followers","following_url":"https://api.github.com/users/jperrin/following{/other_user}","gists_url":"https://api.github.com/users/jperrin/gists{/gist_id}","starred_url":"https://api.github.com/users/jperrin/starred{/owner}{/repo}","subscriptions_url":"https://api.github.com/users/jperrin/subscriptions","organizations_url":"https://api.github.com/users/jperrin/orgs","repos_url":"https://api.github.com/users/jperrin/repos","events_url":"https://api.github.com/users/jperrin/events{/privacy}","received_events_url":"https://api.github.com/users/jperrin/received_events","type":"User","site_admin":false,"contributions":77},{"login":"mohammedzee1000","id":8547729,"avatar_url":"https://avatars0.githubusercontent.com/u/8547729?v=3","gravatar_id":"","url":"https://api.github.com/users/mohammedzee1000","html_url":"https://github.com/mohammedzee1000","followers_url":"https://api.github.com/users/mohammedzee1000/followers","following_url":"https://api.github.com/users/mohammedzee1000/following{/other_user}","gists_url":"https://api.github.com/users/mohammedzee1000/gists{/gist_id}","starred_url":"https://api.github.com/users/mohammedzee1000/starred{/owner}{/repo}","subscriptions_url":"https://api.github.com/users/mohammedzee1000/subscriptions","organizations_url":"https://api.github.com/users/mohammedzee1000/orgs","repos_url":"https://api.github.com/users/mohammedzee1000/repos","events_url":"https://api.github.com/users/mohammedzee1000/events{/privacy}","received_events_url":"https://api.github.com/users/mohammedzee1000/received_events","type":"User","site_admin":false,"contributions":21},{"login":"goern","id":260331,"avatar_url":"https://avatars0.githubusercontent.com/u/260331?v=3","gravatar_id":"","url":"https://api.github.com/users/goern","html_url":"https://github.com/goern","followers_url":"https://api.github.com/users/goern/followers","following_url":"https://api.github.com/users/goern/following{/other_user}","gists_url":"https://api.github.com/users/goern/gists{/gist_id}","starred_url":"https://api.github.com/users/goern/starred{/owner}{/repo}","subscriptions_url":"https://api.github.com/users/goern/subscriptions","organizations_url":"https://api.github.com/users/goern/orgs","repos_url":"https://api.github.com/users/goern/repos","events_url":"https://api.github.com/users/goern/events{/privacy}","received_events_url":"https://api.github.com/users/goern/received_events","type":"User","site_admin":false,"contributions":13},{"login":"jasonbrooks","id":113114,"avatar_url":"https://avatars3.githubusercontent.com/u/113114?v=3","gravatar_id":"","url":"https://api.github.com/users/jasonbrooks","html_url":"https://github.com/jasonbrooks","followers_url":"https://api.github.com/users/jasonbrooks/followers","following_url":"https://api.github.com/users/jasonbrooks/following{/other_user}","gists_url":"https://api.github.com/users/jasonbrooks/gists{/gist_id}","starred_url":"https://api.github.com/users/jasonbrooks/starred{/owner}{/repo}","subscriptions_url":"https://api.github.com/users/jasonbrooks/subscriptions","organizations_url":"https://api.github.com/users/jasonbrooks/orgs","repos_url":"https://api.github.com/users/jasonbrooks/repos","events_url":"https://api.github.com/users/jasonbrooks/events{/privacy}","received_events_url":"https://api.github.com/users/jasonbrooks/received_events","type":"User","site_admin":false,"contributions":8},{"login":"kbsingh","id":207967,"avatar_url":"https://avatars2.githubusercontent.com/u/207967?v=3","gravatar_id":"","url":"https://api.github.com/users/kbsingh","html_url":"https://github.com/kbsingh","followers_url":"https://api.github.com/users/kbsingh/followers","following_url":"https://api.github.com/users/kbsingh/following{/other_user}","gists_url":"https://api.github.com/users/kbsingh/gists{/gist_id}","starred_url":"https://api.github.com/users/kbsingh/starred{/owner}{/repo}","subscriptions_url":"https://api.github.com/users/kbsingh/subscriptions","organizations_url":"https://api.github.com/users/kbsingh/orgs","repos_url":"https://api.github.com/users/kbsingh/repos","events_url":"https://api.github.com/users/kbsingh/events{/privacy}","received_events_url":"https://api.github.com/users/kbsingh/received_events","type":"User","site_admin":false,"contributions":7},{"login":"jimperrin","id":1240010,"avatar_url":"https://avatars0.githubusercontent.com/u/1240010?v=3","gravatar_id":"","url":"https://api.github.com/users/jimperrin","html_url":"https://github.com/jimperrin","followers_url":"https://api.github.com/users/jimperrin/followers","following_url":"https://api.github.com/users/jimperrin/following{/other_user}","gists_url":"https://api.github.com/users/jimperrin/gists{/gist_id}","starred_url":"https://api.github.com/users/jimperrin/starred{/owner}{/repo}","subscriptions_url":"https://api.github.com/users/jimperrin/subscriptions","organizations_url":"https://api.github.com/users/jimperrin/orgs","repos_url":"https://api.github.com/users/jimperrin/repos","events_url":"https://api.github.com/users/jimperrin/events{/privacy}","received_events_url":"https://api.github.com/users/jimperrin/received_events","type":"User","site_admin":false,"contributions":5},{"login":"dustymabe","id":4530030,"avatar_url":"https://avatars1.githubusercontent.com/u/4530030?v=3","gravatar_id":"","url":"https://api.github.com/users/dustymabe","html_url":"https://github.com/dustymabe","followers_url":"https://api.github.com/users/dustymabe/followers","following_url":"https://api.github.com/users/dustymabe/following{/other_user}","gists_url":"https://api.github.com/users/dustymabe/gists{/gist_id}","starred_url":"https://api.github.com/users/dustymabe/starred{/owner}{/repo}","subscriptions_url":"https://api.github.com/users/dustymabe/subscriptions","organizations_url":"https://api.github.com/users/dustymabe/orgs","repos_url":"https://api.github.com/users/dustymabe/repos","events_url":"https://api.github.com/users/dustymabe/events{/privacy}","received_events_url":"https://api.github.com/users/dustymabe/received_events","type":"User","site_admin":false,"contributions":4},{"login":"maxamillion","id":839000,"avatar_url":"https://avatars2.githubusercontent.com/u/839000?v=3","gravatar_id":"","url":"https://api.github.com/users/maxamillion","html_url":"https://github.com/maxamillion","followers_url":"https://api.github.com/users/maxamillion/followers","following_url":"https://api.github.com/users/maxamillion/following{/other_user}","gists_url":"https://api.github.com/users/maxamillion/gists{/gist_id}","starred_url":"https://api.github.com/users/maxamillion/starred{/owner}{/repo}","subscriptions_url":"https://api.github.com/users/maxamillion/subscriptions","organizations_url":"https://api.github.com/users/maxamillion/orgs","repos_url":"https://api.github.com/users/maxamillion/repos","events_url":"https://api.github.com/users/maxamillion/events{/privacy}","received_events_url":"https://api.github.com/users/maxamillion/received_events","type":"User","site_admin":false,"contributions":2},{"login":"egmar","id":243891,"avatar_url":"https://avatars1.githubusercontent.com/u/243891?v=3","gravatar_id":"","url":"https://api.github.com/users/egmar","html_url":"https://github.com/egmar","followers_url":"https://api.github.com/users/egmar/followers","following_url":"https://api.github.com/users/egmar/following{/other_user}","gists_url":"https://api.github.com/users/egmar/gists{/gist_id}","starred_url":"https://api.github.com/users/egmar/starred{/owner}{/repo}","subscriptions_url":"https://api.github.com/users/egmar/subscriptions","organizations_url":"https://api.github.com/users/egmar/orgs","repos_url":"https://api.github.com/users/egmar/repos","events_url":"https://api.github.com/users/egmar/events{/privacy}","received_events_url":"https://api.github.com/users/egmar/received_events","type":"User","site_admin":false,"contributions":2},{"login":"adelton","id":2536912,"avatar_url":"https://avatars1.githubusercontent.com/u/2536912?v=3","gravatar_id":"","url":"https://api.github.com/users/adelton","html_url":"https://github.com/adelton","followers_url":"https://api.github.com/users/adelton/followers","following_url":"https://api.github.com/users/adelton/following{/other_user}","gists_url":"https://api.github.com/users/adelton/gists{/gist_id}","starred_url":"https://api.github.com/users/adelton/starred{/owner}{/repo}","subscriptions_url":"https://api.github.com/users/adelton/subscriptions","organizations_url":"https://api.github.com/users/adelton/orgs","repos_url":"https://api.github.com/users/adelton/repos","events_url":"https://api.github.com/users/adelton/events{/privacy}","received_events_url":"https://api.github.com/users/adelton/received_events","type":"User","site_admin":false,"contributions":2},{"login":"r4j4h","id":703007,"avatar_url":"https://avatars2.githubusercontent.com/u/703007?v=3","gravatar_id":"","url":"https://api.github.com/users/r4j4h","html_url":"https://github.com/r4j4h","followers_url":"https://api.github.com/users/r4j4h/followers","following_url":"https://api.github.com/users/r4j4h/following{/other_user}","gists_url":"https://api.github.com/users/r4j4h/gists{/gist_id}","starred_url":"https://api.github.com/users/r4j4h/starred{/owner}{/repo}","subscriptions_url":"https://api.github.com/users/r4j4h/subscriptions","organizations_url":"https://api.github.com/users/r4j4h/orgs","repos_url":"https://api.github.com/users/r4j4h/repos","events_url":"https://api.github.com/users/r4j4h/events{/privacy}","received_events_url":"https://api.github.com/users/r4j4h/received_events","type":"User","site_admin":false,"contributions":2},{"login":"DirectXMan12","id":119737,"avatar_url":"https://avatars2.githubusercontent.com/u/119737?v=3","gravatar_id":"","url":"https://api.github.com/users/DirectXMan12","html_url":"https://github.com/DirectXMan12","followers_url":"https://api.github.com/users/DirectXMan12/followers","following_url":"https://api.github.com/users/DirectXMan12/following{/other_user}","gists_url":"https://api.github.com/users/DirectXMan12/gists{/gist_id}","starred_url":"https://api.github.com/users/DirectXMan12/starred{/owner}{/repo}","subscriptions_url":"https://api.github.com/users/DirectXMan12/subscriptions","organizations_url":"https://api.github.com/users/DirectXMan12/orgs","repos_url":"https://api.github.com/users/DirectXMan12/repos","events_url":"https://api.github.com/users/DirectXMan12/events{/privacy}","received_events_url":"https://api.github.com/users/DirectXMan12/received_events","type":"User","site_admin":false,"contributions":2},{"login":"vpavlin","id":4759808,"avatar_url":"https://avatars1.githubusercontent.com/u/4759808?v=3","gravatar_id":"","url":"https://api.github.com/users/vpavlin","html_url":"https://github.com/vpavlin","followers_url":"https://api.github.com/users/vpavlin/followers","following_url":"https://api.github.com/users/vpavlin/following{/other_user}","gists_url":"https://api.github.com/users/vpavlin/gists{/gist_id}","starred_url":"https://api.github.com/users/vpavlin/starred{/owner}{/repo}","subscriptions_url":"https://api.github.com/users/vpavlin/subscriptions","organizations_url":"https://api.github.com/users/vpavlin/orgs","repos_url":"https://api.github.com/users/vpavlin/repos","events_url":"https://api.github.com/users/vpavlin/events{/privacy}","received_events_url":"https://api.github.com/users/vpavlin/received_events","type":"User","site_admin":false,"contributions":2},{"login":"procrypt","id":11635662,"avatar_url":"https://avatars1.githubusercontent.com/u/11635662?v=3","gravatar_id":"","url":"https://api.github.com/users/procrypt","html_url":"https://github.com/procrypt","followers_url":"https://api.github.com/users/procrypt/followers","following_url":"https://api.github.com/users/procrypt/following{/other_user}","gists_url":"https://api.github.com/users/procrypt/gists{/gist_id}","starred_url":"https://api.github.com/users/procrypt/starred{/owner}{/repo}","subscriptions_url":"https://api.github.com/users/procrypt/subscriptions","organizations_url":"https://api.github.com/users/procrypt/orgs","repos_url":"https://api.github.com/users/procrypt/repos","events_url":"https://api.github.com/users/procrypt/events{/privacy}","received_events_url":"https://api.github.com/users/procrypt/received_events","type":"User","site_admin":false,"contributions":1},{"login":"bamachrn","id":8213617,"avatar_url":"https://avatars3.githubusercontent.com/u/8213617?v=3","gravatar_id":"","url":"https://api.github.com/users/bamachrn","html_url":"https://github.com/bamachrn","followers_url":"https://api.github.com/users/bamachrn/followers","following_url":"https://api.github.com/users/bamachrn/following{/other_user}","gists_url":"https://api.github.com/users/bamachrn/gists{/gist_id}","starred_url":"https://api.github.com/users/bamachrn/starred{/owner}{/repo}","subscriptions_url":"https://api.github.com/users/bamachrn/subscriptions","organizations_url":"https://api.github.com/users/bamachrn/orgs","repos_url":"https://api.github.com/users/bamachrn/repos","events_url":"https://api.github.com/users/bamachrn/events{/privacy}","received_events_url":"https://api.github.com/users/bamachrn/received_events","type":"User","site_admin":false,"contributions":1},{"login":"liubin","id":1212008,"avatar_url":"https://avatars2.githubusercontent.com/u/1212008?v=3","gravatar_id":"","url":"https://api.github.com/users/liubin","html_url":"https://github.com/liubin","followers_url":"https://api.github.com/users/liubin/followers","following_url":"https://api.github.com/users/liubin/following{/other_user}","gists_url":"https://api.github.com/users/liubin/gists{/gist_id}","starred_url":"https://api.github.com/users/liubin/starred{/owner}{/repo}","subscriptions_url":"https://api.github.com/users/liubin/subscriptions","organizations_url":"https://api.github.com/users/liubin/orgs","repos_url":"https://api.github.com/users/liubin/repos","events_url":"https://api.github.com/users/liubin/events{/privacy}","received_events_url":"https://api.github.com/users/liubin/received_events","type":"User","site_admin":false,"contributions":1},{"login":"deinarson","id":5897168,"avatar_url":"https://avatars0.githubusercontent.com/u/5897168?v=3","gravatar_id":"","url":"https://api.github.com/users/deinarson","html_url":"https://github.com/deinarson","followers_url":"https://api.github.com/users/deinarson/followers","following_url":"https://api.github.com/users/deinarson/following{/other_user}","gists_url":"https://api.github.com/users/deinarson/gists{/gist_id}","starred_url":"https://api.github.com/users/deinarson/starred{/owner}{/repo}","subscriptions_url":"https://api.github.com/users/deinarson/subscriptions","organizations_url":"https://api.github.com/users/deinarson/orgs","repos_url":"https://api.github.com/users/deinarson/repos","events_url":"https://api.github.com/users/deinarson/events{/privacy}","received_events_url":"https://api.github.com/users/deinarson/received_events","type":"User","site_admin":false,"contributions":1},{"login":"gammamatrix","id":524724,"avatar_url":"https://avatars1.githubusercontent.com/u/524724?v=3","gravatar_id":"","url":"https://api.github.com/users/gammamatrix","html_url":"https://github.com/gammamatrix","followers_url":"https://api.github.com/users/gammamatrix/followers","following_url":"https://api.github.com/users/gammamatrix/following{/other_user}","gists_url":"https://api.github.com/users/gammamatrix/gists{/gist_id}","starred_url":"https://api.github.com/users/gammamatrix/starred{/owner}{/repo}","subscriptions_url":"https://api.github.com/users/gammamatrix/subscriptions","organizations_url":"https://api.github.com/users/gammamatrix/orgs","repos_url":"https://api.github.com/users/gammamatrix/repos","events_url":"https://api.github.com/users/gammamatrix/events{/privacy}","received_events_url":"https://api.github.com/users/gammamatrix/received_events","type":"User","site_admin":false,"contributions":1},{"login":"vaceletm","id":216464,"avatar_url":"https://avatars3.githubusercontent.com/u/216464?v=3","gravatar_id":"","url":"https://api.github.com/users/vaceletm","html_url":"https://github.com/vaceletm","followers_url":"https://api.github.com/users/vaceletm/followers","following_url":"https://api.github.com/users/vaceletm/following{/other_user}","gists_url":"https://api.github.com/users/vaceletm/gists{/gist_id}","starred_url":"https://api.github.com/users/vaceletm/starred{/owner}{/repo}","subscriptions_url":"https://api.github.com/users/vaceletm/subscriptions","organizations_url":"https://api.github.com/users/vaceletm/orgs","repos_url":"https://api.github.com/users/vaceletm/repos","events_url":"https://api.github.com/users/vaceletm/events{/privacy}","received_events_url":"https://api.github.com/users/vaceletm/received_events","type":"User","site_admin":false,"contributions":1},{"login":"klaver","id":4640721,"avatar_url":"https://avatars0.githubusercontent.com/u/4640721?v=3","gravatar_id":"","url":"https://api.github.com/users/klaver","html_url":"https://github.com/klaver","followers_url":"https://api.github.com/users/klaver/followers","following_url":"https://api.github.com/users/klaver/following{/other_user}","gists_url":"https://api.github.com/users/klaver/gists{/gist_id}","starred_url":"https://api.github.com/users/klaver/starred{/owner}{/repo}","subscriptions_url":"https://api.github.com/users/klaver/subscriptions","organizations_url":"https://api.github.com/users/klaver/orgs","repos_url":"https://api.github.com/users/klaver/repos","events_url":"https://api.github.com/users/klaver/events{/privacy}","received_events_url":"https://api.github.com/users/klaver/received_events","type":"User","site_admin":false,"contributions":1},{"login":"rtnpro","id":231684,"avatar_url":"https://avatars1.githubusercontent.com/u/231684?v=3","gravatar_id":"","url":"https://api.github.com/users/rtnpro","html_url":"https://github.com/rtnpro","followers_url":"https://api.github.com/users/rtnpro/followers","following_url":"https://api.github.com/users/rtnpro/following{/other_user}","gists_url":"https://api.github.com/users/rtnpro/gists{/gist_id}","starred_url":"https://api.github.com/users/rtnpro/starred{/owner}{/repo}","subscriptions_url":"https://api.github.com/users/rtnpro/subscriptions","organizations_url":"https://api.github.com/users/rtnpro/orgs","repos_url":"https://api.github.com/users/rtnpro/repos","events_url":"https://api.github.com/users/rtnpro/events{/privacy}","received_events_url":"https://api.github.com/users/rtnpro/received_events","type":"User","site_admin":false,"contributions":1},{"login":"kadel","id":57206,"avatar_url":"https://avatars2.githubusercontent.com/u/57206?v=3","gravatar_id":"","url":"https://api.github.com/users/kadel","html_url":"https://github.com/kadel","followers_url":"https://api.github.com/users/kadel/followers","following_url":"https://api.github.com/users/kadel/following{/other_user}","gists_url":"https://api.github.com/users/kadel/gists{/gist_id}","starred_url":"https://api.github.com/users/kadel/starred{/owner}{/repo}","subscriptions_url":"https://api.github.com/users/kadel/subscriptions","organizations_url":"https://api.github.com/users/kadel/orgs","repos_url":"https://api.github.com/users/kadel/repos","events_url":"https://api.github.com/users/kadel/events{/privacy}","received_events_url":"https://api.github.com/users/kadel/received_events","type":"User","site_admin":false,"contributions":1},{"login":"tnozicka","id":11869554,"avatar_url":"https://avatars1.githubusercontent.com/u/11869554?v=3","gravatar_id":"","url":"https://api.github.com/users/tnozicka","html_url":"https://github.com/tnozicka","followers_url":"https://api.github.com/users/tnozicka/followers","following_url":"https://api.github.com/users/tnozicka/following{/other_user}","gists_url":"https://api.github.com/users/tnozicka/gists{/gist_id}","starred_url":"https://api.github.com/users/tnozicka/starred{/owner}{/repo}","subscriptions_url":"https://api.github.com/users/tnozicka/subscriptions","organizations_url":"https://api.github.com/users/tnozicka/orgs","repos_url":"https://api.github.com/users/tnozicka/repos","events_url":"https://api.github.com/users/tnozicka/events{/privacy}","received_events_url":"https://api.github.com/users/tnozicka/received_events","type":"User","site_admin":false,"contributions":1},{"login":"qiawei","id":7943836,"avatar_url":"https://avatars3.githubusercontent.com/u/7943836?v=3","gravatar_id":"","url":"https://api.github.com/users/qiawei","html_url":"https://github.com/qiawei","followers_url":"https://api.github.com/users/qiawei/followers","following_url":"https://api.github.com/users/qiawei/following{/other_user}","gists_url":"https://api.github.com/users/qiawei/gists{/gist_id}","starred_url":"https://api.github.com/users/qiawei/starred{/owner}{/repo}","subscriptions_url":"https://api.github.com/users/qiawei/subscriptions","organizations_url":"https://api.github.com/users/qiawei/orgs","repos_url":"https://api.github.com/users/qiawei/repos","events_url":"https://api.github.com/users/qiawei/events{/privacy}","received_events_url":"https://api.github.com/users/qiawei/received_events","type":"User","site_admin":false,"contributions":1},{"login":"smallfish","id":105860,"avatar_url":"https://avatars0.githubusercontent.com/u/105860?v=3","gravatar_id":"","url":"https://api.github.com/users/smallfish","html_url":"https://github.com/smallfish","followers_url":"https://api.github.com/users/smallfish/followers","following_url":"https://api.github.com/users/smallfish/following{/other_user}","gists_url":"https://api.github.com/users/smallfish/gists{/gist_id}","starred_url":"https://api.github.com/users/smallfish/starred{/owner}{/repo}","subscriptions_url":"https://api.github.com/users/smallfish/subscriptions","organizations_url":"https://api.github.com/users/smallfish/orgs","repos_url":"https://api.github.com/users/smallfish/repos","events_url":"https://api.github.com/users/smallfish/events{/privacy}","received_events_url":"https://api.github.com/users/smallfish/received_events","type":"User","site_admin":false,"contributions":1},{"login":"vroetman","id":105869,"avatar_url":"https://avatars1.githubusercontent.com/u/105869?v=3","gravatar_id":"","url":"https://api.github.com/users/vroetman","html_url":"https://github.com/vroetman","followers_url":"https://api.github.com/users/vroetman/followers","following_url":"https://api.github.com/users/vroetman/following{/other_user}","gists_url":"https://api.github.com/users/vroetman/gists{/gist_id}","starred_url":"https://api.github.com/users/vroetman/starred{/owner}{/repo}","subscriptions_url":"https://api.github.com/users/vroetman/subscriptions","organizations_url":"https://api.github.com/users/vroetman/orgs","repos_url":"https://api.github.com/users/vroetman/repos","events_url":"https://api.github.com/users/vroetman/events{/privacy}","received_events_url":"https://api.github.com/users/vroetman/received_events","type":"User","site_admin":false,"contributions":1},{"login":"wings27","id":5449378,"avatar_url":"https://avatars3.githubusercontent.com/u/5449378?v=3","gravatar_id":"","url":"https://api.github.com/users/wings27","html_url":"https://github.com/wings27","followers_url":"https://api.github.com/users/wings27/followers","following_url":"https://api.github.com/users/wings27/following{/other_user}","gists_url":"https://api.github.com/users/wings27/gists{/gist_id}","starred_url":"https://api.github.com/users/wings27/starred{/owner}{/repo}","subscriptions_url":"https://api.github.com/users/wings27/subscriptions","organizations_url":"https://api.github.com/users/wings27/orgs","repos_url":"https://api.github.com/users/wings27/repos","events_url":"https://api.github.com/users/wings27/events{/privacy}","received_events_url":"https://api.github.com/users/wings27/received_events","type":"User","site_admin":false,"contributions":1},{"login":"xrow","id":295491,"avatar_url":"https://avatars1.githubusercontent.com/u/295491?v=3","gravatar_id":"","url":"https://api.github.com/users/xrow","html_url":"https://github.com/xrow","followers_url":"https://api.github.com/users/xrow/followers","following_url":"https://api.github.com/users/xrow/following{/other_user}","gists_url":"https://api.github.com/users/xrow/gists{/gist_id}","starred_url":"https://api.github.com/users/xrow/starred{/owner}{/repo}","subscriptions_url":"https://api.github.com/users/xrow/subscriptions","organizations_url":"https://api.github.com/users/xrow/orgs","repos_url":"https://api.github.com/users/xrow/repos","events_url":"https://api.github.com/users/xrow/events{/privacy}","received_events_url":"https://api.github.com/users/xrow/received_events","type":"User","site_admin":false,"contributions":1},{"login":"yukihane","id":827785,"avatar_url":"https://avatars0.githubusercontent.com/u/827785?v=3","gravatar_id":"","url":"https://api.github.com/users/yukihane","html_url":"https://github.com/yukihane","followers_url":"https://api.github.com/users/yukihane/followers","following_url":"https://api.github.com/users/yukihane/following{/other_user}","gists_url":"https://api.github.com/users/yukihane/gists{/gist_id}","starred_url":"https://api.github.com/users/yukihane/starred{/owner}{/repo}","subscriptions_url":"https://api.github.com/users/yukihane/subscriptions","organizations_url":"https://api.github.com/users/yukihane/orgs","repos_url":"https://api.github.com/users/yukihane/repos","events_url":"https://api.github.com/users/yukihane/events{/privacy}","received_events_url":"https://api.github.com/users/yukihane/received_events","type":"User","site_admin":false,"contributions":1}]