[{"login":"ivanovnikolay","id":1043943,"avatar_url":"https://avatars2.githubusercontent.com/u/1043943?v=3","gravatar_id":"","url":"https://api.github.com/users/ivanovnikolay","html_url":"https://github.com/ivanovnikolay","followers_url":"https://api.github.com/users/ivanovnikolay/followers","following_url":"https://api.github.com/users/ivanovnikolay/following{/other_user}","gists_url":"https://api.github.com/users/ivanovnikolay/gists{/gist_id}","starred_url":"https://api.github.com/users/ivanovnikolay/starred{/owner}{/repo}","subscriptions_url":"https://api.github.com/users/ivanovnikolay/subscriptions","organizations_url":"https://api.github.com/users/ivanovnikolay/orgs","repos_url":"https://api.github.com/users/ivanovnikolay/repos","events_url":"https://api.github.com/users/ivanovnikolay/events{/privacy}","received_events_url":"https://api.github.com/users/ivanovnikolay/received_events","type":"User","site_admin":false,"contributions":15},{"login":"alexeybannov","id":8578518,"avatar_url":"https://avatars2.githubusercontent.com/u/8578518?v=3","gravatar_id":"","url":"https://api.github.com/users/alexeybannov","html_url":"https://github.com/alexeybannov","followers_url":"https://api.github.com/users/alexeybannov/followers","following_url":"https://api.github.com/users/alexeybannov/following{/other_user}","gists_url":"https://api.github.com/users/alexeybannov/gists{/gist_id}","starred_url":"https://api.github.com/users/alexeybannov/starred{/owner}{/repo}","subscriptions_url":"https://api.github.com/users/alexeybannov/subscriptions","organizations_url":"https://api.github.com/users/alexeybannov/orgs","repos_url":"https://api.github.com/users/alexeybannov/repos","events_url":"https://api.github.com/users/alexeybannov/events{/privacy}","received_events_url":"https://api.github.com/users/alexeybannov/received_events","type":"User","site_admin":false,"contributions":11},{"login":"alexandervnuchkov","id":12795158,"avatar_url":"https://avatars1.githubusercontent.com/u/12795158?v=3","gravatar_id":"","url":"https://api.github.com/users/alexandervnuchkov","html_url":"https://github.com/alexandervnuchkov","followers_url":"https://api.github.com/users/alexandervnuchkov/followers","following_url":"https://api.github.com/users/alexandervnuchkov/following{/other_user}","gists_url":"https://api.github.com/users/alexandervnuchkov/gists{/gist_id}","starred_url":"https://api.github.com/users/alexandervnuchkov/starred{/owner}{/repo}","subscriptions_url":"https://api.github.com/users/alexandervnuchkov/subscriptions","organizations_url":"https://api.github.com/users/alexandervnuchkov/orgs","repos_url":"https://api.github.com/users/alexandervnuchkov/repos","events_url":"https://api.github.com/users/alexandervnuchkov/events{/privacy}","received_events_url":"https://api.github.com/users/alexandervnuchkov/received_events","type":"User","site_admin":false,"contributions":7},{"login":"AlexeySafronov","id":8580545,"avatar_url":"https://avatars0.githubusercontent.com/u/8580545?v=3","gravatar_id":"","url":"https://api.github.com/users/AlexeySafronov","html_url":"https://github.com/AlexeySafronov","followers_url":"https://api.github.com/users/AlexeySafronov/followers","following_url":"https://api.github.com/users/AlexeySafronov/following{/other_user}","gists_url":"https://api.github.com/users/AlexeySafronov/gists{/gist_id}","starred_url":"https://api.github.com/users/AlexeySafronov/starred{/owner}{/repo}","subscriptions_url":"https://api.github.com/users/AlexeySafronov/subscriptions","organizations_url":"https://api.github.com/users/AlexeySafronov/orgs","repos_url":"https://api.github.com/users/AlexeySafronov/repos","events_url":"https://api.github.com/users/AlexeySafronov/events{/privacy}","received_events_url":"https://api.github.com/users/AlexeySafronov/received_events","type":"User","site_admin":false,"contributions":1}]