[{"login":"cesarsouza","id":528455,"avatar_url":"https://avatars3.githubusercontent.com/u/528455?v=3","gravatar_id":"","url":"https://api.github.com/users/cesarsouza","html_url":"https://github.com/cesarsouza","followers_url":"https://api.github.com/users/cesarsouza/followers","following_url":"https://api.github.com/users/cesarsouza/following{/other_user}","gists_url":"https://api.github.com/users/cesarsouza/gists{/gist_id}","starred_url":"https://api.github.com/users/cesarsouza/starred{/owner}{/repo}","subscriptions_url":"https://api.github.com/users/cesarsouza/subscriptions","organizations_url":"https://api.github.com/users/cesarsouza/orgs","repos_url":"https://api.github.com/users/cesarsouza/repos","events_url":"https://api.github.com/users/cesarsouza/events{/privacy}","received_events_url":"https://api.github.com/users/cesarsouza/received_events","type":"User","site_admin":false,"contributions":1339},{"login":"anders9ustafsson","id":6515030,"avatar_url":"https://avatars2.githubusercontent.com/u/6515030?v=3","gravatar_id":"","url":"https://api.github.com/users/anders9ustafsson","html_url":"https://github.com/anders9ustafsson","followers_url":"https://api.github.com/users/anders9ustafsson/followers","following_url":"https://api.github.com/users/anders9ustafsson/following{/other_user}","gists_url":"https://api.github.com/users/anders9ustafsson/gists{/gist_id}","starred_url":"https://api.github.com/users/anders9ustafsson/starred{/owner}{/repo}","subscriptions_url":"https://api.github.com/users/anders9ustafsson/subscriptions","organizations_url":"https://api.github.com/users/anders9ustafsson/orgs","repos_url":"https://api.github.com/users/anders9ustafsson/repos","events_url":"https://api.github.com/users/anders9ustafsson/events{/privacy}","received_events_url":"https://api.github.com/users/anders9ustafsson/received_events","type":"User","site_admin":false,"contributions":41},{"login":"DiegoCatalano","id":5301914,"avatar_url":"https://avatars1.githubusercontent.com/u/5301914?v=3","gravatar_id":"","url":"https://api.github.com/users/DiegoCatalano","html_url":"https://github.com/DiegoCatalano","followers_url":"https://api.github.com/users/DiegoCatalano/followers","following_url":"https://api.github.com/users/DiegoCatalano/following{/other_user}","gists_url":"https://api.github.com/users/DiegoCatalano/gists{/gist_id}","starred_url":"https://api.github.com/users/DiegoCatalano/starred{/owner}{/repo}","subscriptions_url":"https://api.github.com/users/DiegoCatalano/subscriptions","organizations_url":"https://api.github.com/users/DiegoCatalano/orgs","repos_url":"https://api.github.com/users/DiegoCatalano/repos","events_url":"https://api.github.com/users/DiegoCatalano/events{/privacy}","received_events_url":"https://api.github.com/users/DiegoCatalano/received_events","type":"User","site_admin":false,"contributions":22},{"login":"glyphard","id":852344,"avatar_url":"https://avatars1.githubusercontent.com/u/852344?v=3","gravatar_id":"","url":"https://api.github.com/users/glyphard","html_url":"https://github.com/glyphard","followers_url":"https://api.github.com/users/glyphard/followers","following_url":"https://api.github.com/users/glyphard/following{/other_user}","gists_url":"https://api.github.com/users/glyphard/gists{/gist_id}","starred_url":"https://api.github.com/users/glyphard/starred{/owner}{/repo}","subscriptions_url":"https://api.github.com/users/glyphard/subscriptions","organizations_url":"https://api.github.com/users/glyphard/orgs","repos_url":"https://api.github.com/users/glyphard/repos","events_url":"https://api.github.com/users/glyphard/events{/privacy}","received_events_url":"https://api.github.com/users/glyphard/received_events","type":"User","site_admin":false,"contributions":8},{"login":"fo40225","id":10285869,"avatar_url":"https://avatars2.githubusercontent.com/u/10285869?v=3","gravatar_id":"","url":"https://api.github.com/users/fo40225","html_url":"https://github.com/fo40225","followers_url":"https://api.github.com/users/fo40225/followers","following_url":"https://api.github.com/users/fo40225/following{/other_user}","gists_url":"https://api.github.com/users/fo40225/gists{/gist_id}","starred_url":"https://api.github.com/users/fo40225/starred{/owner}{/repo}","subscriptions_url":"https://api.github.com/users/fo40225/subscriptions","organizations_url":"https://api.github.com/users/fo40225/orgs","repos_url":"https://api.github.com/users/fo40225/repos","events_url":"https://api.github.com/users/fo40225/events{/privacy}","received_events_url":"https://api.github.com/users/fo40225/received_events","type":"User","site_admin":false,"contributions":6},{"login":"NikolasMarkou","id":1175820,"avatar_url":"https://avatars3.githubusercontent.com/u/1175820?v=3","gravatar_id":"","url":"https://api.github.com/users/NikolasMarkou","html_url":"https://github.com/NikolasMarkou","followers_url":"https://api.github.com/users/NikolasMarkou/followers","following_url":"https://api.github.com/users/NikolasMarkou/following{/other_user}","gists_url":"https://api.github.com/users/NikolasMarkou/gists{/gist_id}","starred_url":"https://api.github.com/users/NikolasMarkou/starred{/owner}{/repo}","subscriptions_url":"https://api.github.com/users/NikolasMarkou/subscriptions","organizations_url":"https://api.github.com/users/NikolasMarkou/orgs","repos_url":"https://api.github.com/users/NikolasMarkou/repos","events_url":"https://api.github.com/users/NikolasMarkou/events{/privacy}","received_events_url":"https://api.github.com/users/NikolasMarkou/received_events","type":"User","site_admin":false,"contributions":6},{"login":"hzawary","id":13867408,"avatar_url":"https://avatars0.githubusercontent.com/u/13867408?v=3","gravatar_id":"","url":"https://api.github.com/users/hzawary","html_url":"https://github.com/hzawary","followers_url":"https://api.github.com/users/hzawary/followers","following_url":"https://api.github.com/users/hzawary/following{/other_user}","gists_url":"https://api.github.com/users/hzawary/gists{/gist_id}","starred_url":"https://api.github.com/users/hzawary/starred{/owner}{/repo}","subscriptions_url":"https://api.github.com/users/hzawary/subscriptions","organizations_url":"https://api.github.com/users/hzawary/orgs","repos_url":"https://api.github.com/users/hzawary/repos","events_url":"https://api.github.com/users/hzawary/events{/privacy}","received_events_url":"https://api.github.com/users/hzawary/received_events","type":"User","site_admin":false,"contributions":5},{"login":"andrewkirillov","id":9928551,"avatar_url":"https://avatars0.githubusercontent.com/u/9928551?v=3","gravatar_id":"","url":"https://api.github.com/users/andrewkirillov","html_url":"https://github.com/andrewkirillov","followers_url":"https://api.github.com/users/andrewkirillov/followers","following_url":"https://api.github.com/users/andrewkirillov/following{/other_user}","gists_url":"https://api.github.com/users/andrewkirillov/gists{/gist_id}","starred_url":"https://api.github.com/users/andrewkirillov/starred{/owner}{/repo}","subscriptions_url":"https://api.github.com/users/andrewkirillov/subscriptions","organizations_url":"https://api.github.com/users/andrewkirillov/orgs","repos_url":"https://api.github.com/users/andrewkirillov/repos","events_url":"https://api.github.com/users/andrewkirillov/events{/privacy}","received_events_url":"https://api.github.com/users/andrewkirillov/received_events","type":"User","site_admin":false,"contributions":4},{"login":"rftemer","id":8952494,"avatar_url":"https://avatars2.githubusercontent.com/u/8952494?v=3","gravatar_id":"","url":"https://api.github.com/users/rftemer","html_url":"https://github.com/rftemer","followers_url":"https://api.github.com/users/rftemer/followers","following_url":"https://api.github.com/users/rftemer/following{/other_user}","gists_url":"https://api.github.com/users/rftemer/gists{/gist_id}","starred_url":"https://api.github.com/users/rftemer/starred{/owner}{/repo}","subscriptions_url":"https://api.github.com/users/rftemer/subscriptions","organizations_url":"https://api.github.com/users/rftemer/orgs","repos_url":"https://api.github.com/users/rftemer/repos","events_url":"https://api.github.com/users/rftemer/events{/privacy}","received_events_url":"https://api.github.com/users/rftemer/received_events","type":"User","site_admin":false,"contributions":3},{"login":"wanghongqi","id":1303178,"avatar_url":"https://avatars1.githubusercontent.com/u/1303178?v=3","gravatar_id":"","url":"https://api.github.com/users/wanghongqi","html_url":"https://github.com/wanghongqi","followers_url":"https://api.github.com/users/wanghongqi/followers","following_url":"https://api.github.com/users/wanghongqi/following{/other_user}","gists_url":"https://api.github.com/users/wanghongqi/gists{/gist_id}","starred_url":"https://api.github.com/users/wanghongqi/starred{/owner}{/repo}","subscriptions_url":"https://api.github.com/users/wanghongqi/subscriptions","organizations_url":"https://api.github.com/users/wanghongqi/orgs","repos_url":"https://api.github.com/users/wanghongqi/repos","events_url":"https://api.github.com/users/wanghongqi/events{/privacy}","received_events_url":"https://api.github.com/users/wanghongqi/received_events","type":"User","site_admin":false,"contributions":3},{"login":"aggieben","id":1321,"avatar_url":"https://avatars2.githubusercontent.com/u/1321?v=3","gravatar_id":"","url":"https://api.github.com/users/aggieben","html_url":"https://github.com/aggieben","followers_url":"https://api.github.com/users/aggieben/followers","following_url":"https://api.github.com/users/aggieben/following{/other_user}","gists_url":"https://api.github.com/users/aggieben/gists{/gist_id}","starred_url":"https://api.github.com/users/aggieben/starred{/owner}{/repo}","subscriptions_url":"https://api.github.com/users/aggieben/subscriptions","organizations_url":"https://api.github.com/users/aggieben/orgs","repos_url":"https://api.github.com/users/aggieben/repos","events_url":"https://api.github.com/users/aggieben/events{/privacy}","received_events_url":"https://api.github.com/users/aggieben/received_events","type":"User","site_admin":false,"contributions":2},{"login":"EdHubbell","id":1578632,"avatar_url":"https://avatars0.githubusercontent.com/u/1578632?v=3","gravatar_id":"","url":"https://api.github.com/users/EdHubbell","html_url":"https://github.com/EdHubbell","followers_url":"https://api.github.com/users/EdHubbell/followers","following_url":"https://api.github.com/users/EdHubbell/following{/other_user}","gists_url":"https://api.github.com/users/EdHubbell/gists{/gist_id}","starred_url":"https://api.github.com/users/EdHubbell/starred{/owner}{/repo}","subscriptions_url":"https://api.github.com/users/EdHubbell/subscriptions","organizations_url":"https://api.github.com/users/EdHubbell/orgs","repos_url":"https://api.github.com/users/EdHubbell/repos","events_url":"https://api.github.com/users/EdHubbell/events{/privacy}","received_events_url":"https://api.github.com/users/EdHubbell/received_events","type":"User","site_admin":false,"contributions":2},{"login":"MasoudRahmani","id":5321268,"avatar_url":"https://avatars0.githubusercontent.com/u/5321268?v=3","gravatar_id":"","url":"https://api.github.com/users/MasoudRahmani","html_url":"https://github.com/MasoudRahmani","followers_url":"https://api.github.com/users/MasoudRahmani/followers","following_url":"https://api.github.com/users/MasoudRahmani/following{/other_user}","gists_url":"https://api.github.com/users/MasoudRahmani/gists{/gist_id}","starred_url":"https://api.github.com/users/MasoudRahmani/starred{/owner}{/repo}","subscriptions_url":"https://api.github.com/users/MasoudRahmani/subscriptions","organizations_url":"https://api.github.com/users/MasoudRahmani/orgs","repos_url":"https://api.github.com/users/MasoudRahmani/repos","events_url":"https://api.github.com/users/MasoudRahmani/events{/privacy}","received_events_url":"https://api.github.com/users/MasoudRahmani/received_events","type":"User","site_admin":false,"contributions":2},{"login":"MikkelPorse","id":7520688,"avatar_url":"https://avatars3.githubusercontent.com/u/7520688?v=3","gravatar_id":"","url":"https://api.github.com/users/MikkelPorse","html_url":"https://github.com/MikkelPorse","followers_url":"https://api.github.com/users/MikkelPorse/followers","following_url":"https://api.github.com/users/MikkelPorse/following{/other_user}","gists_url":"https://api.github.com/users/MikkelPorse/gists{/gist_id}","starred_url":"https://api.github.com/users/MikkelPorse/starred{/owner}{/repo}","subscriptions_url":"https://api.github.com/users/MikkelPorse/subscriptions","organizations_url":"https://api.github.com/users/MikkelPorse/orgs","repos_url":"https://api.github.com/users/MikkelPorse/repos","events_url":"https://api.github.com/users/MikkelPorse/events{/privacy}","received_events_url":"https://api.github.com/users/MikkelPorse/received_events","type":"User","site_admin":false,"contributions":2},{"login":"stefan-j","id":2664883,"avatar_url":"https://avatars0.githubusercontent.com/u/2664883?v=3","gravatar_id":"","url":"https://api.github.com/users/stefan-j","html_url":"https://github.com/stefan-j","followers_url":"https://api.github.com/users/stefan-j/followers","following_url":"https://api.github.com/users/stefan-j/following{/other_user}","gists_url":"https://api.github.com/users/stefan-j/gists{/gist_id}","starred_url":"https://api.github.com/users/stefan-j/starred{/owner}{/repo}","subscriptions_url":"https://api.github.com/users/stefan-j/subscriptions","organizations_url":"https://api.github.com/users/stefan-j/orgs","repos_url":"https://api.github.com/users/stefan-j/repos","events_url":"https://api.github.com/users/stefan-j/events{/privacy}","received_events_url":"https://api.github.com/users/stefan-j/received_events","type":"User","site_admin":false,"contributions":1},{"login":"stbentia","id":4593783,"avatar_url":"https://avatars1.githubusercontent.com/u/4593783?v=3","gravatar_id":"","url":"https://api.github.com/users/stbentia","html_url":"https://github.com/stbentia","followers_url":"https://api.github.com/users/stbentia/followers","following_url":"https://api.github.com/users/stbentia/following{/other_user}","gists_url":"https://api.github.com/users/stbentia/gists{/gist_id}","starred_url":"https://api.github.com/users/stbentia/starred{/owner}{/repo}","subscriptions_url":"https://api.github.com/users/stbentia/subscriptions","organizations_url":"https://api.github.com/users/stbentia/orgs","repos_url":"https://api.github.com/users/stbentia/repos","events_url":"https://api.github.com/users/stbentia/events{/privacy}","received_events_url":"https://api.github.com/users/stbentia/received_events","type":"User","site_admin":false,"contributions":1},{"login":"MPPECS","id":11852912,"avatar_url":"https://avatars0.githubusercontent.com/u/11852912?v=3","gravatar_id":"","url":"https://api.github.com/users/MPPECS","html_url":"https://github.com/MPPECS","followers_url":"https://api.github.com/users/MPPECS/followers","following_url":"https://api.github.com/users/MPPECS/following{/other_user}","gists_url":"https://api.github.com/users/MPPECS/gists{/gist_id}","starred_url":"https://api.github.com/users/MPPECS/starred{/owner}{/repo}","subscriptions_url":"https://api.github.com/users/MPPECS/subscriptions","organizations_url":"https://api.github.com/users/MPPECS/orgs","repos_url":"https://api.github.com/users/MPPECS/repos","events_url":"https://api.github.com/users/MPPECS/events{/privacy}","received_events_url":"https://api.github.com/users/MPPECS/received_events","type":"User","site_admin":false,"contributions":1},{"login":"david-durrleman","id":5435154,"avatar_url":"https://avatars2.githubusercontent.com/u/5435154?v=3","gravatar_id":"","url":"https://api.github.com/users/david-durrleman","html_url":"https://github.com/david-durrleman","followers_url":"https://api.github.com/users/david-durrleman/followers","following_url":"https://api.github.com/users/david-durrleman/following{/other_user}","gists_url":"https://api.github.com/users/david-durrleman/gists{/gist_id}","starred_url":"https://api.github.com/users/david-durrleman/starred{/owner}{/repo}","subscriptions_url":"https://api.github.com/users/david-durrleman/subscriptions","organizations_url":"https://api.github.com/users/david-durrleman/orgs","repos_url":"https://api.github.com/users/david-durrleman/repos","events_url":"https://api.github.com/users/david-durrleman/events{/privacy}","received_events_url":"https://api.github.com/users/david-durrleman/received_events","type":"User","site_admin":false,"contributions":1},{"login":"dsblank","id":168568,"avatar_url":"https://avatars2.githubusercontent.com/u/168568?v=3","gravatar_id":"","url":"https://api.github.com/users/dsblank","html_url":"https://github.com/dsblank","followers_url":"https://api.github.com/users/dsblank/followers","following_url":"https://api.github.com/users/dsblank/following{/other_user}","gists_url":"https://api.github.com/users/dsblank/gists{/gist_id}","starred_url":"https://api.github.com/users/dsblank/starred{/owner}{/repo}","subscriptions_url":"https://api.github.com/users/dsblank/subscriptions","organizations_url":"https://api.github.com/users/dsblank/orgs","repos_url":"https://api.github.com/users/dsblank/repos","events_url":"https://api.github.com/users/dsblank/events{/privacy}","received_events_url":"https://api.github.com/users/dsblank/received_events","type":"User","site_admin":false,"contributions":1},{"login":"okh1","id":13621287,"avatar_url":"https://avatars2.githubusercontent.com/u/13621287?v=3","gravatar_id":"","url":"https://api.github.com/users/okh1","html_url":"https://github.com/okh1","followers_url":"https://api.github.com/users/okh1/followers","following_url":"https://api.github.com/users/okh1/following{/other_user}","gists_url":"https://api.github.com/users/okh1/gists{/gist_id}","starred_url":"https://api.github.com/users/okh1/starred{/owner}{/repo}","subscriptions_url":"https://api.github.com/users/okh1/subscriptions","organizations_url":"https://api.github.com/users/okh1/orgs","repos_url":"https://api.github.com/users/okh1/repos","events_url":"https://api.github.com/users/okh1/events{/privacy}","received_events_url":"https://api.github.com/users/okh1/received_events","type":"User","site_admin":false,"contributions":1},{"login":"hanswolff","id":1478348,"avatar_url":"https://avatars0.githubusercontent.com/u/1478348?v=3","gravatar_id":"","url":"https://api.github.com/users/hanswolff","html_url":"https://github.com/hanswolff","followers_url":"https://api.github.com/users/hanswolff/followers","following_url":"https://api.github.com/users/hanswolff/following{/other_user}","gists_url":"https://api.github.com/users/hanswolff/gists{/gist_id}","starred_url":"https://api.github.com/users/hanswolff/starred{/owner}{/repo}","subscriptions_url":"https://api.github.com/users/hanswolff/subscriptions","organizations_url":"https://api.github.com/users/hanswolff/orgs","repos_url":"https://api.github.com/users/hanswolff/repos","events_url":"https://api.github.com/users/hanswolff/events{/privacy}","received_events_url":"https://api.github.com/users/hanswolff/received_events","type":"User","site_admin":false,"contributions":1},{"login":"haf","id":193115,"avatar_url":"https://avatars3.githubusercontent.com/u/193115?v=3","gravatar_id":"","url":"https://api.github.com/users/haf","html_url":"https://github.com/haf","followers_url":"https://api.github.com/users/haf/followers","following_url":"https://api.github.com/users/haf/following{/other_user}","gists_url":"https://api.github.com/users/haf/gists{/gist_id}","starred_url":"https://api.github.com/users/haf/starred{/owner}{/repo}","subscriptions_url":"https://api.github.com/users/haf/subscriptions","organizations_url":"https://api.github.com/users/haf/orgs","repos_url":"https://api.github.com/users/haf/repos","events_url":"https://api.github.com/users/haf/events{/privacy}","received_events_url":"https://api.github.com/users/haf/received_events","type":"User","site_admin":false,"contributions":1},{"login":"kdbanman","id":1323521,"avatar_url":"https://avatars2.githubusercontent.com/u/1323521?v=3","gravatar_id":"","url":"https://api.github.com/users/kdbanman","html_url":"https://github.com/kdbanman","followers_url":"https://api.github.com/users/kdbanman/followers","following_url":"https://api.github.com/users/kdbanman/following{/other_user}","gists_url":"https://api.github.com/users/kdbanman/gists{/gist_id}","starred_url":"https://api.github.com/users/kdbanman/starred{/owner}{/repo}","subscriptions_url":"https://api.github.com/users/kdbanman/subscriptions","organizations_url":"https://api.github.com/users/kdbanman/orgs","repos_url":"https://api.github.com/users/kdbanman/repos","events_url":"https://api.github.com/users/kdbanman/events{/privacy}","received_events_url":"https://api.github.com/users/kdbanman/received_events","type":"User","site_admin":false,"contributions":1},{"login":"siadatmark","id":15884275,"avatar_url":"https://avatars1.githubusercontent.com/u/15884275?v=3","gravatar_id":"","url":"https://api.github.com/users/siadatmark","html_url":"https://github.com/siadatmark","followers_url":"https://api.github.com/users/siadatmark/followers","following_url":"https://api.github.com/users/siadatmark/following{/other_user}","gists_url":"https://api.github.com/users/siadatmark/gists{/gist_id}","starred_url":"https://api.github.com/users/siadatmark/starred{/owner}{/repo}","subscriptions_url":"https://api.github.com/users/siadatmark/subscriptions","organizations_url":"https://api.github.com/users/siadatmark/orgs","repos_url":"https://api.github.com/users/siadatmark/repos","events_url":"https://api.github.com/users/siadatmark/events{/privacy}","received_events_url":"https://api.github.com/users/siadatmark/received_events","type":"User","site_admin":false,"contributions":1},{"login":"kulov","id":939355,"avatar_url":"https://avatars2.githubusercontent.com/u/939355?v=3","gravatar_id":"","url":"https://api.github.com/users/kulov","html_url":"https://github.com/kulov","followers_url":"https://api.github.com/users/kulov/followers","following_url":"https://api.github.com/users/kulov/following{/other_user}","gists_url":"https://api.github.com/users/kulov/gists{/gist_id}","starred_url":"https://api.github.com/users/kulov/starred{/owner}{/repo}","subscriptions_url":"https://api.github.com/users/kulov/subscriptions","organizations_url":"https://api.github.com/users/kulov/orgs","repos_url":"https://api.github.com/users/kulov/repos","events_url":"https://api.github.com/users/kulov/events{/privacy}","received_events_url":"https://api.github.com/users/kulov/received_events","type":"User","site_admin":false,"contributions":1},{"login":"MendelMonteiro","id":1752566,"avatar_url":"https://avatars1.githubusercontent.com/u/1752566?v=3","gravatar_id":"","url":"https://api.github.com/users/MendelMonteiro","html_url":"https://github.com/MendelMonteiro","followers_url":"https://api.github.com/users/MendelMonteiro/followers","following_url":"https://api.github.com/users/MendelMonteiro/following{/other_user}","gists_url":"https://api.github.com/users/MendelMonteiro/gists{/gist_id}","starred_url":"https://api.github.com/users/MendelMonteiro/starred{/owner}{/repo}","subscriptions_url":"https://api.github.com/users/MendelMonteiro/subscriptions","organizations_url":"https://api.github.com/users/MendelMonteiro/orgs","repos_url":"https://api.github.com/users/MendelMonteiro/repos","events_url":"https://api.github.com/users/MendelMonteiro/events{/privacy}","received_events_url":"https://api.github.com/users/MendelMonteiro/received_events","type":"User","site_admin":false,"contributions":1},{"login":"PaulARoy","id":6310023,"avatar_url":"https://avatars0.githubusercontent.com/u/6310023?v=3","gravatar_id":"","url":"https://api.github.com/users/PaulARoy","html_url":"https://github.com/PaulARoy","followers_url":"https://api.github.com/users/PaulARoy/followers","following_url":"https://api.github.com/users/PaulARoy/following{/other_user}","gists_url":"https://api.github.com/users/PaulARoy/gists{/gist_id}","starred_url":"https://api.github.com/users/PaulARoy/starred{/owner}{/repo}","subscriptions_url":"https://api.github.com/users/PaulARoy/subscriptions","organizations_url":"https://api.github.com/users/PaulARoy/orgs","repos_url":"https://api.github.com/users/PaulARoy/repos","events_url":"https://api.github.com/users/PaulARoy/events{/privacy}","received_events_url":"https://api.github.com/users/PaulARoy/received_events","type":"User","site_admin":false,"contributions":1},{"login":"pawelsawicz","id":1385487,"avatar_url":"https://avatars1.githubusercontent.com/u/1385487?v=3","gravatar_id":"","url":"https://api.github.com/users/pawelsawicz","html_url":"https://github.com/pawelsawicz","followers_url":"https://api.github.com/users/pawelsawicz/followers","following_url":"https://api.github.com/users/pawelsawicz/following{/other_user}","gists_url":"https://api.github.com/users/pawelsawicz/gists{/gist_id}","starred_url":"https://api.github.com/users/pawelsawicz/starred{/owner}{/repo}","subscriptions_url":"https://api.github.com/users/pawelsawicz/subscriptions","organizations_url":"https://api.github.com/users/pawelsawicz/orgs","repos_url":"https://api.github.com/users/pawelsawicz/repos","events_url":"https://api.github.com/users/pawelsawicz/events{/privacy}","received_events_url":"https://api.github.com/users/pawelsawicz/received_events","type":"User","site_admin":false,"contributions":1},{"login":"nevoroman","id":17815140,"avatar_url":"https://avatars2.githubusercontent.com/u/17815140?v=3","gravatar_id":"","url":"https://api.github.com/users/nevoroman","html_url":"https://github.com/nevoroman","followers_url":"https://api.github.com/users/nevoroman/followers","following_url":"https://api.github.com/users/nevoroman/following{/other_user}","gists_url":"https://api.github.com/users/nevoroman/gists{/gist_id}","starred_url":"https://api.github.com/users/nevoroman/starred{/owner}{/repo}","subscriptions_url":"https://api.github.com/users/nevoroman/subscriptions","organizations_url":"https://api.github.com/users/nevoroman/orgs","repos_url":"https://api.github.com/users/nevoroman/repos","events_url":"https://api.github.com/users/nevoroman/events{/privacy}","received_events_url":"https://api.github.com/users/nevoroman/received_events","type":"User","site_admin":false,"contributions":1},{"login":"gitter-badger","id":8518239,"avatar_url":"https://avatars1.githubusercontent.com/u/8518239?v=3","gravatar_id":"","url":"https://api.github.com/users/gitter-badger","html_url":"https://github.com/gitter-badger","followers_url":"https://api.github.com/users/gitter-badger/followers","following_url":"https://api.github.com/users/gitter-badger/following{/other_user}","gists_url":"https://api.github.com/users/gitter-badger/gists{/gist_id}","starred_url":"https://api.github.com/users/gitter-badger/starred{/owner}{/repo}","subscriptions_url":"https://api.github.com/users/gitter-badger/subscriptions","organizations_url":"https://api.github.com/users/gitter-badger/orgs","repos_url":"https://api.github.com/users/gitter-badger/repos","events_url":"https://api.github.com/users/gitter-badger/events{/privacy}","received_events_url":"https://api.github.com/users/gitter-badger/received_events","type":"User","site_admin":false,"contributions":1}]